setup.py
snapp/__init__.py
snapp/execute.py
snapp/ioc.py
snapp/module.py
snapp.egg-info/PKG-INFO
snapp.egg-info/SOURCES.txt
snapp.egg-info/dependency_links.txt
snapp.egg-info/top_level.txt