Metadata-Version: 1.0
Name: snapp
Version: 0.1.1
Summary: Python framework for building command line applications.
Home-page: https://www.signiant.com
Author: Matthew Corner
Author-email: matt.corner@gmail.com
License: MIT
Platform: UNKNOWN
